autoagents_core/__init__.py
autoagents_core/api/ChatAPI.py
autoagents_core/api/GraphAPI.py
autoagents_core/api/KbAPI.py
autoagents_core/client/ChatClient.py
autoagents_core/client/CrawlClient.py
autoagents_core/client/KbClient.py
autoagents_core/client/MCPClient.py
autoagents_core/client/SupabaseClient.py
autoagents_core/client/__init__.py
autoagents_core/datascience/DSAgent.py
autoagents_core/datascience/__init__.py
autoagents_core/publish/Publisher.py
autoagents_core/publish/__init__.py
autoagents_core/react/ReActAgent.py
autoagents_core/react/__init__.py
autoagents_core/sandbox/E2BSandbox.py
autoagents_core/sandbox/LocalSandbox.py
autoagents_core/sandbox/__init__.py
autoagents_core/slide/README.md
autoagents_core/slide/SlideAgent.py
autoagents_core/slide/__init__.py
autoagents_core/slide/html2pptx_agent.py
autoagents_core/slide/pptx2pptx_agent.py
autoagents_core/tools/ToolManager.py
autoagents_core/tools/__init__.py
autoagents_core/types/ChatTypes.py
autoagents_core/types/GraphTypes.py
autoagents_core/types/KbTypes.py
autoagents_core/types/__init__.py
autoagents_core/utils/__init__.py
autoagents_core/utils/convertor.py
autoagents_core/utils/downloader.py
autoagents_core/utils/extractor.py
autoagents_core/utils/uploader.py
autoagents_core-0.1.4.dist-info/METADATA
autoagents_core-0.1.4.dist-info/WHEEL
autoagents_core-0.1.4.dist-info/RECORD
